Assembly-1.3.0.dist-info/METADATA
Assembly-1.3.0.dist-info/RECORD
Assembly-1.3.0.dist-info/WHEEL
Assembly-1.3.0.dist-info/entry_points.txt
Assembly-1.3.0.dist-info/top_level.txt
assembly/.DS_Store
assembly/__about__.py
assembly/__about__.pyc
assembly/__init__.py
assembly/__init__.pyc
assembly/_db.py
assembly/_extensions.py
assembly/about.py
assembly/asm.py
assembly/asm_db.py
assembly/assembly.py
assembly/cli.py
assembly/cli.pyc
assembly/commander.pyc
assembly/core.py
assembly/core.pyc
assembly/decorators.pyc
assembly/exceptions.pyc
assembly/ext.pyc
assembly/extensions.py
assembly/extensions.pyc
assembly/flasik_db.pyc
assembly/forms.py
assembly/functions.py
assembly/functions.pyc
assembly/plugins.py
assembly/plugins.pyc
assembly/render.pyc
assembly/request.py
assembly/request.pyc
assembly/response.py
assembly/response.pyc
assembly/scripts.py
assembly/signals.pyc
assembly/utils.py
assembly/utils.pyc
assembly/__pycache__/__about__.cpython-36.pyc
assembly/__pycache__/__init__.cpython-36.pyc
assembly/__pycache__/_asm.cpython-36.pyc
assembly/__pycache__/_db.cpython-36.pyc
assembly/__pycache__/_extensions.cpython-36.pyc
assembly/__pycache__/about.cpython-36.pyc
assembly/__pycache__/asm.cpython-36.pyc
assembly/__pycache__/asm_db.cpython-36.pyc
assembly/__pycache__/asm_request.cpython-36.pyc
assembly/__pycache__/assembly.cpython-36 (Mardochee’s MacBook Pro's conflicted copy 2019-12-23).pyc
assembly/__pycache__/assembly.cpython-36.pyc
assembly/__pycache__/cli.cpython-36.pyc
assembly/__pycache__/core.cpython-36.pyc
assembly/__pycache__/extensions.cpython-36.pyc
assembly/__pycache__/flasik_db.cpython-36.pyc
assembly/__pycache__/functions.cpython-36.pyc
assembly/__pycache__/plugins.cpython-36.pyc
assembly/__pycache__/request.cpython-36.pyc
assembly/__pycache__/response.cpython-36.pyc
assembly/__pycache__/scripts.cpython-36 (Mardochee’s MacBook Pro's conflicted copy 2019-12-23).pyc
assembly/__pycache__/scripts.cpython-36.pyc
assembly/__pycache__/signals.cpython-36.pyc
assembly/__pycache__/utils.cpython-36.pyc
assembly/scaffold/.DS_Store
assembly/scaffold/create-api-views/README.md
