Metadata-Version: 2.1
Name: Assembly
Version: 1.3.0
Summary: Assembly is a pythonic object-oriented, mid stack, batteries included framework built on Flask, that adds structure to your Flask application, and group your routes by class.Assembly allows developers to build web applications in much the same way they would build any other object-oriented Python program.Assembly Makes Flask Great Again!
Home-page: https://github.com/mardix/assembly
Author: Mardix
Author-email: mcx2082@gmail.com
License: MIT
Keywords: flask,assembly,templates,views,classy,framework,mvc,blueprint
Platform: any
Classifier: Environment :: Web Environment
Classifier: Intended Audience :: Developers
Classifier: License :: OSI Approved :: BSD License
Classifier: Operating System :: OS Independent
Classifier: Programming Language :: Python
Classifier: Programming Language :: Python :: 3.6
Classifier: Topic :: Internet :: WWW/HTTP :: Dynamic Content
Classifier: Topic :: Software Development :: Libraries :: Python Modules
Requires-Dist: Flask (>=1.0.0)
Requires-Dist: flask-assets (>=0.12)
Requires-Dist: flask-kvsession (>=0.6.2)
Requires-Dist: flask-s3 (>=0.3.3)
Requires-Dist: flask-mail (>=0.9.1)
Requires-Dist: flask-caching (>=1.7.2)
Requires-Dist: flask-cloudy (>=1.0.1)
Requires-Dist: flask-seasurf (>=0.2.2)
Requires-Dist: flask-cors (>=3.0.8)
Requires-Dist: flask-login (>=0.4.1)
Requires-Dist: Active-Alchemy (>=1.0.0)
Requires-Dist: six (>=1.9.0)
Requires-Dist: passlib (<1.8.0,>=1.7.0)
Requires-Dist: bcrypt (>=3.1.7)
Requires-Dist: python-slugify (>=4.0.0)
Requires-Dist: ses-mailer (>=0.13.0)
Requires-Dist: markdown (>=2.6.2)
Requires-Dist: inflection (==0.3.1)
Requires-Dist: click (>=6.2)
Requires-Dist: dicttoxml (>=1.7.4)
Requires-Dist: arrow (>=0.15.2)
Requires-Dist: blinker (>=1.4)
Requires-Dist: itsdangerous (>=1.1.0)
Requires-Dist: requests (>=2.13.0)
Requires-Dist: paginator
Requires-Dist: pyyaml
Requires-Dist: wtforms
Requires-Dist: python-dateutil (<2.8.1)
